{"success":true,"data":[{"target_date":"2026-02-01T00:00:00.000Z","predicted_count":208,"ci80_low":171,"ci80_high":245,"ci95_low":151,"ci95_high":265,"model_version":"4.0.24","weather_data":{"factor":1,"maxTemp":19,"minTemp":14,"weather":"大致多雲。早上相當清涼，日間部分時間有陽光及乾燥。"},"ai_factors":{"type":"突發公衛事件","confidence":"中","description":"衞生防護中心公布新增類鼻疽個案，可能引發高風險群組（長者及長期病患者）因擔憂感染而增加急症室求診意願。","impactFactor":1.05},"created_at":"2026-01-30T19:53:22.051Z"},{"target_date":"2026-02-02T00:00:00.000Z","predicted_count":178,"ci80_low":131,"ci80_high":225,"ci95_low":105,"ci95_high":251,"model_version":"4.0.24","weather_data":{"factor":1,"maxTemp":20,"minTemp":15,"weather":"部分時間有陽光。早上清涼，日間乾燥。"},"ai_factors":{"type":"政策變更","confidence":"中","description":"醫管局急症室分級收費制度生效後，非緊急求診人數持續下降（預計減少15-20%），但『危殆』及『危急』病例比例可能相對增加。","impactFactor":0.85},"created_at":"2026-01-30T19:53:22.056Z"},{"target_date":"2026-02-03T00:00:00.000Z","predicted_count":180,"ci80_low":138,"ci80_high":222,"ci95_low":116,"ci95_high":244,"model_version":"4.0.24","weather_data":{"factor":1,"maxTemp":20,"minTemp":16,"weather":"部分時間有陽光。早上清涼。"},"ai_factors":{"type":"政策變更","confidence":"中","description":"醫管局急症室分級收費制度生效後，非緊急求診人數持續下降（預計減少15-20%），但『危殆』及『危急』病例比例可能相對增加。","impactFactor":0.85},"created_at":"2026-01-30T19:53:22.060Z"},{"target_date":"2026-02-04T00:00:00.000Z","predicted_count":180,"ci80_low":140,"ci80_high":220,"ci95_low":119,"ci95_high":241,"model_version":"4.0.24","weather_data":{"factor":1,"maxTemp":22,"minTemp":17,"weather":"部分時間有陽光。"},"ai_factors":{"type":"政策變更","confidence":"中","description":"醫管局急症室分級收費制度生效後，非緊急求診人數持續下降（預計減少15-20%），但『危殆』及『危急』病例比例可能相對增加。","impactFactor":0.85},"created_at":"2026-01-30T19:53:22.063Z"},{"target_date":"2026-02-05T00:00:00.000Z","predicted_count":181,"ci80_low":140,"ci80_high":222,"ci95_low":118,"ci95_high":244,"model_version":"4.0.24","weather_data":{"factor":1,"maxTemp":23,"minTemp":18,"weather":"部分時間有陽光。"},"ai_factors":{"type":"政策變更","confidence":"中","description":"醫管局急症室分級收費制度生效後，非緊急求診人數持續下降（預計減少15-20%），但『危殆』及『危急』病例比例可能相對增加。","impactFactor":0.85},"created_at":"2026-01-30T19:53:22.067Z"},{"target_date":"2026-02-06T00:00:00.000Z","predicted_count":182,"ci80_low":140,"ci80_high":224,"ci95_low":117,"ci95_high":247,"model_version":"4.0.24","weather_data":{"factor":1,"maxTemp":24,"minTemp":19,"weather":"早晚沿岸有薄霧，日間大致天晴及溫暖。"},"ai_factors":{"type":"政策變更","confidence":"中","description":"醫管局急症室分級收費制度生效後，非緊急求診人數持續下降（預計減少15-20%），但『危殆』及『危急』病例比例可能相對增加。","impactFactor":0.85},"created_at":"2026-01-30T19:53:22.070Z"},{"target_date":"2026-02-07T00:00:00.000Z","predicted_count":215,"ci80_low":165,"ci80_high":265,"ci95_low":139,"ci95_high":291,"model_version":"4.0.24","weather_data":{"factor":1,"maxTemp":22,"minTemp":18,"weather":"短暫時間有陽光。"},"ai_factors":null,"created_at":"2026-01-30T19:53:22.073Z"},{"target_date":"2026-02-08T00:00:00.000Z","predicted_count":215,"ci80_low":171,"ci80_high":259,"ci95_low":147,"ci95_high":283,"model_version":"4.0.24","weather_data":{"factor":1,"maxTemp":21,"minTemp":16,"weather":"部分時間有陽光。早上清涼，日間乾燥。"},"ai_factors":null,"created_at":"2026-01-30T19:53:22.077Z"},{"target_date":"2026-02-09T00:00:00.000Z","predicted_count":216,"ci80_low":159,"ci80_high":273,"ci95_low":129,"ci95_high":303,"model_version":"4.0.24","weather_data":null,"ai_factors":null,"created_at":"2026-01-30T19:53:22.079Z"},{"target_date":"2026-02-10T00:00:00.000Z","predicted_count":216,"ci80_low":166,"ci80_high":266,"ci95_low":140,"ci95_high":292,"model_version":"4.0.24","weather_data":null,"ai_factors":null,"created_at":"2026-01-30T19:53:22.081Z"},{"target_date":"2026-02-11T00:00:00.000Z","predicted_count":216,"ci80_low":168,"ci80_high":264,"ci95_low":143,"ci95_high":289,"model_version":"4.0.24","weather_data":null,"ai_factors":null,"created_at":"2026-01-30T19:53:22.083Z"},{"target_date":"2026-02-12T00:00:00.000Z","predicted_count":216,"ci80_low":167,"ci80_high":265,"ci95_low":141,"ci95_high":291,"model_version":"4.0.24","weather_data":null,"ai_factors":null,"created_at":"2026-01-30T19:53:22.085Z"},{"target_date":"2026-02-13T00:00:00.000Z","predicted_count":216,"ci80_low":166,"ci80_high":266,"ci95_low":140,"ci95_high":292,"model_version":"4.0.24","weather_data":null,"ai_factors":null,"created_at":"2026-01-30T19:53:22.088Z"},{"target_date":"2026-02-14T00:00:00.000Z","predicted_count":215,"ci80_low":157,"ci80_high":273,"ci95_low":126,"ci95_high":304,"model_version":"4.0.24","weather_data":null,"ai_factors":null,"created_at":"2026-01-30T19:53:22.090Z"},{"target_date":"2026-02-15T00:00:00.000Z","predicted_count":215,"ci80_low":163,"ci80_high":267,"ci95_low":135,"ci95_high":295,"model_version":"4.0.24","weather_data":null,"ai_factors":null,"created_at":"2026-01-30T19:53:22.094Z"},{"target_date":"2026-02-16T00:00:00.000Z","predicted_count":216,"ci80_low":150,"ci80_high":282,"ci95_low":114,"ci95_high":318,"model_version":"4.0.24","weather_data":null,"ai_factors":null,"created_at":"2026-01-30T19:53:22.095Z"},{"target_date":"2026-02-17T00:00:00.000Z","predicted_count":199,"ci80_low":141,"ci80_high":257,"ci95_low":110,"ci95_high":288,"model_version":"4.0.24","weather_data":null,"ai_factors":null,"created_at":"2026-01-30T19:53:22.098Z"},{"target_date":"2026-02-18T00:00:00.000Z","predicted_count":199,"ci80_low":144,"ci80_high":254,"ci95_low":114,"ci95_high":284,"model_version":"4.0.24","weather_data":null,"ai_factors":null,"created_at":"2026-01-30T19:53:22.100Z"},{"target_date":"2026-02-19T00:00:00.000Z","predicted_count":199,"ci80_low":143,"ci80_high":255,"ci95_low":113,"ci95_high":285,"model_version":"4.0.24","weather_data":null,"ai_factors":null,"created_at":"2026-01-30T19:53:22.101Z"},{"target_date":"2026-02-20T00:00:00.000Z","predicted_count":216,"ci80_low":159,"ci80_high":273,"ci95_low":128,"ci95_high":304,"model_version":"4.0.24","weather_data":null,"ai_factors":null,"created_at":"2026-01-30T19:53:22.102Z"},{"target_date":"2026-02-21T00:00:00.000Z","predicted_count":215,"ci80_low":148,"ci80_high":282,"ci95_low":113,"ci95_high":317,"model_version":"4.0.24","weather_data":null,"ai_factors":null,"created_at":"2026-01-30T19:53:22.107Z"},{"target_date":"2026-02-22T00:00:00.000Z","predicted_count":215,"ci80_low":156,"ci80_high":274,"ci95_low":124,"ci95_high":306,"model_version":"4.0.24","weather_data":null,"ai_factors":null,"created_at":"2026-01-30T19:53:22.109Z"},{"target_date":"2026-02-23T00:00:00.000Z","predicted_count":216,"ci80_low":140,"ci80_high":292,"ci95_low":100,"ci95_high":332,"model_version":"4.0.24","weather_data":null,"ai_factors":null,"created_at":"2026-01-30T19:53:22.111Z"},{"target_date":"2026-02-24T00:00:00.000Z","predicted_count":216,"ci80_low":150,"ci80_high":282,"ci95_low":115,"ci95_high":317,"model_version":"4.0.24","weather_data":null,"ai_factors":null,"created_at":"2026-01-30T19:53:22.112Z"},{"target_date":"2026-02-25T00:00:00.000Z","predicted_count":216,"ci80_low":153,"ci80_high":279,"ci95_low":120,"ci95_high":312,"model_version":"4.0.24","weather_data":null,"ai_factors":null,"created_at":"2026-01-30T19:53:22.114Z"},{"target_date":"2026-02-26T00:00:00.000Z","predicted_count":216,"ci80_low":152,"ci80_high":280,"ci95_low":118,"ci95_high":314,"model_version":"4.0.24","weather_data":null,"ai_factors":null,"created_at":"2026-01-30T19:53:22.116Z"},{"target_date":"2026-02-27T00:00:00.000Z","predicted_count":216,"ci80_low":151,"ci80_high":281,"ci95_low":117,"ci95_high":315,"model_version":"4.0.24","weather_data":null,"ai_factors":null,"created_at":"2026-01-30T19:53:22.118Z"},{"target_date":"2026-02-28T00:00:00.000Z","predicted_count":215,"ci80_low":140,"ci80_high":290,"ci95_low":100,"ci95_high":330,"model_version":"4.0.24","weather_data":null,"ai_factors":null,"created_at":"2026-01-30T19:53:22.120Z"},{"target_date":"2026-03-01T00:00:00.000Z","predicted_count":215,"ci80_low":148,"ci80_high":282,"ci95_low":112,"ci95_high":318,"model_version":"4.0.24","weather_data":null,"ai_factors":null,"created_at":"2026-01-30T19:53:22.126Z"},{"target_date":"2026-03-02T00:00:00.000Z","predicted_count":215,"ci80_low":130,"ci80_high":300,"ci95_low":85,"ci95_high":345,"model_version":"4.0.24","weather_data":null,"ai_factors":null,"created_at":"2026-01-30T19:53:22.128Z"}],"dateRange":{"start":"2026-02-01","end":"2026-03-02"}}
